dane_workflows/__init__.py
dane_workflows/data_processing.py
dane_workflows/data_provider.py
dane_workflows/exporter.py
dane_workflows/runner.py
dane_workflows/status.py
dane_workflows/status_monitor.py
dane_workflows/task_scheduler.py
dane_workflows/util/base_util.py
dane_workflows/util/dane_query_util.py
dane_workflows/util/dane_util.py
dane_workflows-0.2.3.dist-info/LICENSE
dane_workflows-0.2.3.dist-info/WHEEL
dane_workflows-0.2.3.dist-info/METADATA
dane_workflows-0.2.3.dist-info/RECORD
