Metadata-Version: 2.1
Name: dane-workflows
Version: 0.2.3
Summary: Library providing batch upload & monitoring for (DANE) processing environments
Home-page: https://github.com/beeldengeluid/dane-workflows
License: Apache-2.0
Author: jblom
Author-email: jblom@beeldengeluid.nl
Requires-Python: >=3.10,<4.0
Classifier: Development Status :: 4 - Beta
Classifier: Intended Audience :: Developers
Classifier: Intended Audience :: Science/Research
Classifier: License :: OSI Approved :: Apache Software License
Classifier: Programming Language :: Python :: 3
Classifier: Programming Language :: Python :: 3.10
Classifier: Topic :: Scientific/Engineering :: Artificial Intelligence
Classifier: Topic :: Software Development :: Libraries :: Python Modules
Requires-Dist: dane (>=0.3.3,<0.4.0)
Requires-Dist: pika (>=1.2.1,<2.0.0)
Requires-Dist: requests (>=2.28.0,<3.0.0)
Requires-Dist: slack-sdk (>=3.18.1,<4.0.0)
Requires-Dist: types-PyYAML (>=6.0.10,<7.0.0)
Requires-Dist: yacs (>=0.1.8,<0.2.0)
Project-URL: Repository, https://github.com/beeldengeluid/dane-workflows
